{"generatedAt":"2026-07-16T18:01:49.845Z","elapsedSeconds":18,"marketStatus":"open","universeGeneratedAt":"2026-07-15T22:32:32.977Z","universeCount":2317,"scannedCount":2317,"criteria":{"rvolThreshold":3,"priceChangeLimit":0.02,"avgVolumeWindow":"5d","minElapsedMin":30},"count":19,"signals":[{"ticker":"MTNE","name":"CH4 Natural Solutions Corporati","price":9.87,"priceChangePct":0.1,"todayVolume":1165979,"avg5dVolume":50420,"rvol":33.24,"elapsedMin":271,"mcap":293888032},{"ticker":"AMSS","name":"AMASS Brands Inc.","price":1.35,"priceChangePct":0,"todayVolume":809286,"avg5dVolume":104780,"rvol":11.1,"elapsedMin":271,"mcap":15422826},{"ticker":"WENN","name":"Wen Acquisition Corp","price":10.32,"priceChangePct":0.11,"todayVolume":429716,"avg5dVolume":60730,"rvol":10.17,"elapsedMin":271,"mcap":386780800},{"ticker":"EVAC","name":"EQV Ventures Acquisition Corp. ","price":10.22,"priceChangePct":0.15,"todayVolume":326415,"avg5dVolume":51380,"rvol":9.13,"elapsedMin":271,"mcap":596752640},{"ticker":"WNC","name":"Wabash National Corporation","price":12.6,"priceChangePct":-0.32,"todayVolume":4152424,"avg5dVolume":726330,"rvol":8.22,"elapsedMin":271,"mcap":514118976},{"ticker":"VACI","name":"Viking Acquisition Corp. I","price":10.16,"priceChangePct":-0.1,"todayVolume":538246,"avg5dVolume":98930,"rvol":7.82,"elapsedMin":271,"mcap":311880000},{"ticker":"NHIC","name":"NewHold Investment Corp III","price":10.68,"priceChangePct":-0.65,"todayVolume":274198,"avg5dVolume":50510,"rvol":7.8,"elapsedMin":271,"mcap":296284960},{"ticker":"APMC","name":"AmperCap Acquisition Company","price":9.89,"priceChangePct":-0.2,"todayVolume":296607,"avg5dVolume":81220,"rvol":5.25,"elapsedMin":271,"mcap":197789488},{"ticker":"NCI","name":"Neo-Concept International Group","price":11.74,"priceChangePct":-1.26,"todayVolume":669081,"avg5dVolume":198100,"rvol":4.85,"elapsedMin":271,"mcap":28110958},{"ticker":"KRO","name":"Kronos Worldwide Inc","price":6.63,"priceChangePct":-1.19,"todayVolume":968227,"avg5dVolume":289780,"rvol":4.8,"elapsedMin":271,"mcap":772006464},{"ticker":"GSRV","name":"GSR V Acquisition Corp. Class A ordinary shares","price":9.84,"priceChangePct":-0.1,"todayVolume":261466,"avg5dVolume":79725,"rvol":4.71,"elapsedMin":271,"mcap":365948512},{"ticker":"CCIX","name":"Churchill Capital Corp IX","price":10.86,"priceChangePct":0.05,"todayVolume":718560,"avg5dVolume":239490,"rvol":4.31,"elapsedMin":271,"mcap":397788128},{"ticker":"BBCQ","name":"Bleichroeder Acquisition Corp. ","price":10.29,"priceChangePct":-0.05,"todayVolume":232666,"avg5dVolume":85150,"rvol":3.93,"elapsedMin":271,"mcap":394449984},{"ticker":"IPFX","name":"Inflection Point Acquisition Co","price":10.14,"priceChangePct":-0.59,"todayVolume":145927,"avg5dVolume":56350,"rvol":3.72,"elapsedMin":271,"mcap":344079968},{"ticker":"ALIS","name":"Calisa Acquisition Corp","price":10.16,"priceChangePct":0.1,"todayVolume":137574,"avg5dVolume":54930,"rvol":3.6,"elapsedMin":271,"mcap":85539120},{"ticker":"JOF","name":"Japan Smaller Capitalization Fu","price":11.46,"priceChangePct":-0.83,"todayVolume":145858,"avg5dVolume":61150,"rvol":3.43,"elapsedMin":271,"mcap":327539808},{"ticker":"PESI","name":"Perma-Fix Environmental Service","price":14.67,"priceChangePct":-1.08,"todayVolume":911169,"avg5dVolume":393270,"rvol":3.33,"elapsedMin":271,"mcap":314448672},{"ticker":"SCD","name":"LMP Capital and Income Fund Inc","price":15.4,"priceChangePct":-0.19,"todayVolume":158981,"avg5dVolume":70270,"rvol":3.25,"elapsedMin":271,"mcap":353444768},{"ticker":"MNTK","name":"Montauk Renewables, Inc.","price":1.71,"priceChangePct":0.29,"todayVolume":253042,"avg5dVolume":116470,"rvol":3.12,"elapsedMin":271,"mcap":241979936}]}
