{"generatedAt":"2026-06-25T20:31:33.542Z","elapsedSeconds":21,"marketStatus":"open","universeGeneratedAt":"2026-06-24T22:32:18.323Z","universeCount":2432,"scannedCount":2432,"criteria":{"rvolThreshold":3,"priceChangeLimit":0.02,"avgVolumeWindow":"5d","minElapsedMin":30},"count":15,"signals":[{"ticker":"DMII","name":"Drugs Made In America Acquisiti","price":10.07,"priceChangePct":-0.1,"todayVolume":1500102,"avg5dVolume":58490,"rvol":25.65,"elapsedMin":390,"mcap":643370048},{"ticker":"PBK","name":"PowerBank Corporation","price":0.73,"priceChangePct":-1.93,"todayVolume":32746933,"avg5dVolume":2687440,"rvol":12.19,"elapsedMin":390,"mcap":34959328},{"ticker":"FERA","name":"Fifth Era Acquisition Corp I","price":10.43,"priceChangePct":0,"todayVolume":900784,"avg5dVolume":90670,"rvol":9.93,"elapsedMin":390,"mcap":326108224},{"ticker":"OTGA","name":"OTG Acquisition Corp. I","price":10.16,"priceChangePct":0.1,"todayVolume":482355,"avg5dVolume":56140,"rvol":8.59,"elapsedMin":390,"mcap":358041248},{"ticker":"JANX","name":"Janux Therapeutics, Inc.","price":14.58,"priceChangePct":-0.41,"todayVolume":6246748,"avg5dVolume":978150,"rvol":6.39,"elapsedMin":390,"mcap":892810944},{"ticker":"PRA","name":"ProAssurance Corporation","price":25,"priceChangePct":0,"todayVolume":2998415,"avg5dVolume":561210,"rvol":5.34,"elapsedMin":390,"mcap":1290193152},{"ticker":"HFFG","name":"HF Foods Group Inc.","price":1.8,"priceChangePct":1.69,"todayVolume":559370,"avg5dVolume":107140,"rvol":5.22,"elapsedMin":390,"mcap":94651488},{"ticker":"TJGC","name":"TJGC Group Limited","price":4.37,"priceChangePct":0.23,"todayVolume":555818,"avg5dVolume":111620,"rvol":4.98,"elapsedMin":390,"mcap":44036000},{"ticker":"TACO","name":"Berto Acquisition Corp.","price":10.4,"priceChangePct":0.1,"todayVolume":199521,"avg5dVolume":50350,"rvol":3.96,"elapsedMin":390,"mcap":389819840},{"ticker":"UTL","name":"UNITIL Corporation","price":52.42,"priceChangePct":-1.11,"todayVolume":520827,"avg5dVolume":133230,"rvol":3.91,"elapsedMin":390,"mcap":953692928},{"ticker":"AXG","name":"Solowin Holdings","price":3.3,"priceChangePct":0,"todayVolume":406820,"avg5dVolume":106350,"rvol":3.83,"elapsedMin":390,"mcap":628497600},{"ticker":"DYAI","name":"Dyadic International, Inc.","price":0.74,"priceChangePct":1.37,"todayVolume":570590,"avg5dVolume":160580,"rvol":3.55,"elapsedMin":390,"mcap":26636692},{"ticker":"THQ","name":"Tekla Healthcare Opportunies Fu","price":18.33,"priceChangePct":1.55,"todayVolume":399963,"avg5dVolume":123120,"rvol":3.25,"elapsedMin":390,"mcap":747946432},{"ticker":"ONL","name":"Orion Properties Inc.","price":2.74,"priceChangePct":-0.72,"todayVolume":923808,"avg5dVolume":288380,"rvol":3.2,"elapsedMin":390,"mcap":156850992},{"ticker":"AEXA","name":"American Exceptionalism Acquisi","price":11.5,"priceChangePct":0.61,"todayVolume":250845,"avg5dVolume":80940,"rvol":3.1,"elapsedMin":390,"mcap":565335936}]}
