{"generatedAt":"2026-06-26T18:31:46.081Z","elapsedSeconds":20,"marketStatus":"open","universeGeneratedAt":"2026-06-25T22:32:04.033Z","universeCount":2431,"scannedCount":2431,"criteria":{"rvolThreshold":3,"priceChangeLimit":0.02,"avgVolumeWindow":"5d","minElapsedMin":30},"count":13,"signals":[{"ticker":"PBK","name":"PowerBank Corporation","price":0.72,"priceChangePct":-1.04,"todayVolume":58064471,"avg5dVolume":2651920,"rvol":28.33,"elapsedMin":301,"mcap":34283148},{"ticker":"OTGA","name":"OTG Acquisition Corp. I","price":10.16,"priceChangePct":0,"todayVolume":482355,"avg5dVolume":74620,"rvol":8.36,"elapsedMin":301,"mcap":358393984},{"ticker":"COCH","name":"Envoy Medical, Inc.","price":0.68,"priceChangePct":0.51,"todayVolume":483035,"avg5dVolume":113060,"rvol":5.53,"elapsedMin":301,"mcap":51827508},{"ticker":"ANIX","name":"Anixa Biosciences, Inc.","price":2.58,"priceChangePct":-1.53,"todayVolume":943425,"avg5dVolume":224050,"rvol":5.45,"elapsedMin":301,"mcap":89140424},{"ticker":"XAIR","name":"Beyond Air, Inc.","price":0.48,"priceChangePct":-0.04,"todayVolume":1144680,"avg5dVolume":292450,"rvol":5.06,"elapsedMin":301,"mcap":6058218},{"ticker":"AXG","name":"Solowin Holdings","price":3.26,"priceChangePct":-1.21,"todayVolume":451892,"avg5dVolume":116580,"rvol":5.02,"elapsedMin":301,"mcap":628497600},{"ticker":"FAMI","name":"Farmmi, Inc. Ordinary Shares","price":1.28,"priceChangePct":0,"todayVolume":560371,"avg5dVolume":157020,"rvol":4.62,"elapsedMin":301,"mcap":17683468},{"ticker":"PRA","name":"ProAssurance Corporation","price":25,"priceChangePct":0,"todayVolume":3381556,"avg5dVolume":1080570,"rvol":4.05,"elapsedMin":301,"mcap":1290193152},{"ticker":"AEXA","name":"American Exceptionalism Acquisi","price":11.51,"priceChangePct":0.09,"todayVolume":298656,"avg5dVolume":108870,"rvol":3.55,"elapsedMin":301,"mcap":568798208},{"ticker":"SMJF","name":"SMJ International Holdings Inc.","price":5.31,"priceChangePct":-0.75,"todayVolume":1289443,"avg5dVolume":487300,"rvol":3.42,"elapsedMin":301,"mcap":148221744},{"ticker":"LOT","name":"Lotus Technology Inc.","price":1.08,"priceChangePct":0,"todayVolume":142603,"avg5dVolume":56230,"rvol":3.28,"elapsedMin":301,"mcap":699985152},{"ticker":"MSN","name":"Emerson Radio Corporation","price":0.34,"priceChangePct":0.41,"todayVolume":301490,"avg5dVolume":123920,"rvol":3.15,"elapsedMin":301,"mcap":7230255},{"ticker":"RFI","name":"Cohen & Steers Total Return Rea","price":11.32,"priceChangePct":1.57,"todayVolume":237165,"avg5dVolume":101550,"rvol":3.02,"elapsedMin":301,"mcap":298248128}]}
