{"generatedAt":"2026-06-08T21:31:16.472Z","elapsedSeconds":17,"marketStatus":"open","universeGeneratedAt":"2026-06-05T22:31:56.945Z","universeCount":2395,"scannedCount":2395,"criteria":{"rvolThreshold":3,"priceChangeLimit":0.02,"avgVolumeWindow":"5d","minElapsedMin":30},"count":4,"signals":[{"ticker":"VVOS","name":"Vivos Therapeutics, Inc.","price":0.87,"priceChangePct":0.64,"todayVolume":2300314,"avg5dVolume":154880,"rvol":14.85,"elapsedMin":390,"mcap":12011882},{"ticker":"AMAN","name":"Amanat Acquisition Corp","price":10.11,"priceChangePct":0.05,"todayVolume":661913,"avg5dVolume":120510,"rvol":5.49,"elapsedMin":390,"mcap":100458568},{"ticker":"NHP","name":"National Healthcare Properties,","price":14.69,"priceChangePct":0.41,"todayVolume":1530603,"avg5dVolume":282780,"rvol":5.41,"elapsedMin":390,"mcap":1082026496},{"ticker":"JL","name":"J-Long Group Limited","price":6.26,"priceChangePct":1.29,"todayVolume":202829,"avg5dVolume":65600,"rvol":3.09,"elapsedMin":390,"mcap":23510632}]}
